plotlog/__init__.py
plotlog/datacut.py
plotlog/drawgraph.py
plotlog/main.py
plotlog/plotgraph.py
plotlog/selectlog.py
plotlog/setting.py
plotlog/src/__init__.py
plotlog/src/datacut.py
plotlog/src/plotgraph.py
plotlog/src/setting.py
src/__init__.py
src/datacut.py
src/plotgraph.py
src/setting.py
plotlog-0.4.0.dist-info/LICENSE
plotlog-0.4.0.dist-info/METADATA
plotlog-0.4.0.dist-info/WHEEL
plotlog-0.4.0.dist-info/entry_points.txt
plotlog-0.4.0.dist-info/top_level.txt
plotlog-0.4.0.dist-info/RECORD
