Metadata-Version: 2.1
Name: plotlog
Version: 0.4.0
Summary: Plot graph for many log file that is managed by DATE
Home-page: https://github.com/s-naoya/plotlog
Author: SAITO Naoya
Author-email: saito3110.naoya@gmail.com
License: MIT
Keywords: plot graph logfile
Platform: UNKNOWN
Classifier: Programming Language :: Python :: 3.4
Classifier: Programming Language :: Python :: 3.5
Classifier: Programming Language :: Python :: 3.6
Classifier: Programming Language :: Python :: 3.7
Requires-Dist: pandas (>=0.21.1)
Requires-Dist: matplotlib (>=2.1.1)
Requires-Dist: PyYAML (>=3.12)
